adbhoney/__init__.py
adbhoney/config.py
adbhoney/core.py
adbhoney/protocol.py
adbhoney/responses.py
adbhoney/outputs/__init__.py
adbhoney/outputs/output_json.py
adbhoney/outputs/output_log.py
adbhoney-1.0.1.dist-info/LICENSE
adbhoney-1.0.1.dist-info/METADATA
adbhoney-1.0.1.dist-info/WHEEL
adbhoney-1.0.1.dist-info/entry_points.txt
adbhoney-1.0.1.dist-info/top_level.txt
adbhoney-1.0.1.dist-info/RECORD
