Metadata-Version: 2.1
Name: adbhoney
Version: 1.0.1
Summary: A low interaction honeypot for ADB Connections
Home-page: https://github.com/huuck/ADBHoney
License: UNKNOWN
Platform: UNKNOWN
Requires-Python: >=3.6
